Metadata-Version: 2.4
Name: alibaba-cloud-application-management-mcp-server
Version: 1.0.4
Summary: The application management MCP server for Alibaba Cloud
Author-email: Zhao Shuaibo <zhaoshuaibo.zsb@alibaba-inc.com>, Meng Junwei <mengjunwei.mjw@alibaba-inc.com>
License-File: LICENSE
Requires-Python: >=3.10
Requires-Dist: alibaba-cloud-ops-mcp-server
